LICENSE
MANIFEST.in
README.md
setup.py
exma/__init__.py
exma/cluster.py
exma/cn.py
exma/core.py
exma/distances.py
exma/electrochemistry.py
exma/msd.py
exma/rdf.py
exma/statistics.py
exma/vacf.py
exma.egg-info/PKG-INFO
exma.egg-info/SOURCES.txt
exma.egg-info/dependency_links.txt
exma.egg-info/requires.txt
exma.egg-info/top_level.txt
exma/io/__init__.py
exma/io/positions.py
exma/io/reader.py
exma/io/writer.py
exma/lib/__init__.py
exma/lib/cn.c
exma/lib/cn.h
exma/lib/pbc_distances.c
exma/lib/pbc_distances.h
exma/lib/rdf.c
exma/lib/rdf.h