Metadata-Version: 2.1
Name: exma
Version: 0.6.1
Summary: A Python library with C extensions to analyze and manipulate molecular dynamics trajectories and electrochemical data.
Home-page: https://github.com/fernandezfran/exma
Author: Francisco Fernandez
Author-email: ffernandev@gmail.com
License: MIT
Keywords: exma,molecular-dynamics,data-analysis
Classifier: Development Status :: 4 - Beta
Classifier: Intended Audience :: Science/Research
Classifier: License :: OSI Approved :: MIT License
Classifier: Natural Language :: English
Classifier: Operating System :: OS Independent
Classifier: Programming Language :: Python
Classifier: Programming Language :: C
Classifier: Topic :: Scientific/Engineering
License-File: LICENSE
